blamf/__init__.py
blamf/core.py
blamf-0.0.16.dist-info/DESCRIPTION.rst
blamf-0.0.16.dist-info/METADATA
blamf-0.0.16.dist-info/RECORD
blamf-0.0.16.dist-info/WHEEL
blamf-0.0.16.dist-info/metadata.json
blamf-0.0.16.dist-info/top_level.txt
